kozmoai/__init__.py
kozmoai/__main__.py
kozmoai/alembic.ini
kozmoai/main.py
kozmoai/memory.py
kozmoai/middleware.py
kozmoai/py.typed
kozmoai/server.py
kozmoai/settings.py
kozmoai/worker.py
kozmoai/alembic/README
kozmoai/alembic/env.py
kozmoai/alembic/script.py.mako
kozmoai/alembic/versions/006b3990db50_add_unique_constraints.py
kozmoai/alembic/versions/012fb73ac359_add_folder_table.py
kozmoai/alembic/versions/0ae3a2674f32_update_the_columns_that_need_to_change_.py
kozmoai/alembic/versions/0b8757876a7c_.py
kozmoai/alembic/versions/0d60fcbd4e8e_create_vertex_builds_table.py
kozmoai/alembic/versions/1a110b568907_replace_credential_table_with_variable.py
kozmoai/alembic/versions/1c79524817ed_add_unique_constraints_per_user_in_.py
kozmoai/alembic/versions/1d90f8a0efe1_update_description_columns_type.py
kozmoai/alembic/versions/1eab2c3eb45e_event_error.py
kozmoai/alembic/versions/1ef9c4f3765d_.py
kozmoai/alembic/versions/1f4d6df60295_add_default_fields_column.py
kozmoai/alembic/versions/260dbcc8b680_adds_tables.py
kozmoai/alembic/versions/29fe8f1f806b_add_missing_index.py
kozmoai/alembic/versions/2ac71eb9c3ae_adds_credential_table.py
kozmoai/alembic/versions/3bb0ddf32dfb_add_unique_constraints_per_user_in_flow_.py
kozmoai/alembic/versions/4e5980a44eaa_fix_date_times_again.py
kozmoai/alembic/versions/58b28437a398_modify_nullable.py
kozmoai/alembic/versions/5ace73a7f223_new_remove_table_upgrade_op.py
kozmoai/alembic/versions/631faacf5da2_add_webhook_columns.py
kozmoai/alembic/versions/63b9c451fd30_add_icon_and_icon_bg_color_to_flow.py
kozmoai/alembic/versions/67cc006d50bf_add_profile_image_column.py
kozmoai/alembic/versions/6e7b581b5648_fix_nullable.py
kozmoai/alembic/versions/7843803a87b5_store_updates.py
kozmoai/alembic/versions/79e675cb6752_change_datetime_type.py
kozmoai/alembic/versions/7d2162acc8b2_adds_updated_at_and_folder_cols.py
kozmoai/alembic/versions/90be8e2ed91e_create_transactions_table.py
kozmoai/alembic/versions/a72f5cf9c2f9_add_endpoint_name_col.py
kozmoai_base-0.1.8.post1.dist-info/METADATA
kozmoai_base-0.1.8.post1.dist-info/WHEEL
kozmoai_base-0.1.8.post1.dist-info/entry_points.txt
kozmoai_base-0.1.8.post1.dist-info/RECORD
